adafruit_register/__init__.py
adafruit_register/i2c_bcd_alarm.py
adafruit_register/i2c_bcd_datetime.py
adafruit_register/i2c_bit.py
adafruit_register/i2c_bits.py
adafruit_register/i2c_struct.py
adafruit_register/i2c_struct_array.py
adafruit_circuitpython_register-1.9.18.dist-info/LICENSE
adafruit_circuitpython_register-1.9.18.dist-info/METADATA
adafruit_circuitpython_register-1.9.18.dist-info/WHEEL
adafruit_circuitpython_register-1.9.18.dist-info/top_level.txt
adafruit_circuitpython_register-1.9.18.dist-info/RECORD
