Metadata-Version: 2.1
Name: adafruit-circuitpython-register
Version: 1.9.18
Summary: CircuitPython data descriptor classes to represent hardware registers on I2C and SPI devices.
Author-email: Adafruit Industries <circuitpython@adafruit.com>
License: MIT
Project-URL: Homepage, https://github.com/adafruit/Adafruit_CircuitPython_Register
Keywords: adafruit,register,micropython,circuitpython
Classifier: Intended Audience :: Developers
Classifier: Topic :: Software Development :: Libraries
Classifier: Topic :: Software Development :: Embedded Systems
Classifier: Topic :: System :: Hardware
Classifier: License :: OSI Approved :: MIT License
Classifier: Programming Language :: Python :: 3
License-File: LICENSE
Requires-Dist: Adafruit-Blinka
Requires-Dist: adafruit-circuitpython-busdevice
Requires-Dist: typing-extensions~=4.0
Requires-Dist: adafruit-circuitpython-typing==1.*,>=1.3.1
Provides-Extra: optional
